pyspage/__init__.py
pyspage/command.py
pyspage/elements.py
pyspage/layout.py
pyspage/localization.py
pyspage/pyscript.py
pyspage/utils.py
pyspage-0.0.3.dist-info/LICENSE
pyspage-0.0.3.dist-info/METADATA
pyspage-0.0.3.dist-info/WHEEL
pyspage-0.0.3.dist-info/entry_points.txt
pyspage-0.0.3.dist-info/top_level.txt
pyspage-0.0.3.dist-info/RECORD
