Metadata-Version: 2.1
Name: pyspage
Version: 0.0.3
Summary: Quickly build open source web pages for academic purposes in a pythonic and elegant way.
Home-page: https://github.com/chunribu/pyspage/
Author: Jian Jiang
Author-email: jianjiang.bio@gmail.com
License: MIT
Keywords: pyscript pywebio shiny
Classifier: Operating System :: POSIX :: Linux
Classifier: Operating System :: MacOS :: MacOS X
Classifier: Operating System :: Microsoft :: Windows
Classifier: Programming Language :: Python :: 3
Classifier: License :: OSI Approved :: MIT License
License-File: LICENSE
